tomltable/__init__.py
tomltable/errors.py
tomltable/parser.py
tomltable/template.py
tomltable/test_tomltable.py
tomltable/types.py
tomltable-1.1.2.dist-info/METADATA
tomltable-1.1.2.dist-info/WHEEL
tomltable-1.1.2.dist-info/entry_points.txt
tomltable-1.1.2.dist-info/top_level.txt
tomltable-1.1.2.dist-info/RECORD
