Metadata-Version: 2.1
Name: tomltable
Version: 1.1.2
Summary: command-line tool to generate TOML-defined regression tables from JSON data files
Home-page: https://codeberg.org/gnyeki/tomltable
Author: Gabor Nyeki
Requires-Dist: click
Requires-Dist: regex
Requires-Dist: toml
